weather/__init__.py
python_open_weather-1.6.dist-info/LICENSE
python_open_weather-1.6.dist-info/METADATA
python_open_weather-1.6.dist-info/WHEEL
python_open_weather-1.6.dist-info/top_level.txt
python_open_weather-1.6.dist-info/RECORD
