Metadata-Version: 2.1
Name: python-open-weather
Version: 1.6
Summary: Fetch Current Weather Of A Given City (OR) Fetch Current Weather Of A Given City List In A Form Of Table
Home-page: https://github.com/pmk456/python-open-weather
Author: Patan Musthakheem
Author-email: patanmusthakheem786@gmail.com
License: UNKNOWN
Project-URL: Bug Tracker, https://github.com/pmk456/python-open-weather/issues
Platform: UNKNOWN
Classifier: Programming Language :: Python :: 3
Classifier: License :: OSI Approved :: Apache Software License
Classifier: Operating System :: OS Independent
Requires-Python: >=3.0
License-File: LICENSE
